vhelper/__init__.py
vhelper/func_analysis.py
vhelper/kmap.py
vhelper/kmap_gpt.py
vhelper/sim.py
vhelper/utils.py
vhelper-0.0.3.dist-info/licenses/LICENSE
vhelper-0.0.3.dist-info/METADATA
vhelper-0.0.3.dist-info/WHEEL
vhelper-0.0.3.dist-info/top_level.txt
vhelper-0.0.3.dist-info/RECORD
